ligand_mpnn/__init__.py
ligand_mpnn/data_utils.py
ligand_mpnn/model_utils.py
ligand_mpnn/run.py
ligand_mpnn/sc_utils.py
ligand_mpnn/score.py
openfold/__init__.py
openfold/config.py
openfold/data/__init__.py
openfold/data/data_modules.py
openfold/data/data_pipeline.py
openfold/data/data_transforms.py
openfold/data/errors.py
openfold/data/feature_pipeline.py
openfold/data/input_pipeline.py
openfold/data/mmcif_parsing.py
openfold/data/parsers.py
openfold/data/templates.py
openfold/data/tools/__init__.py
openfold/data/tools/hhblits.py
openfold/data/tools/hhsearch.py
openfold/data/tools/jackhmmer.py
openfold/data/tools/kalign.py
openfold/data/tools/utils.py
openfold/np/__init__.py
openfold/np/protein.py
openfold/np/residue_constants.py
openfold/np/relax/__init__.py
openfold/np/relax/amber_minimize.py
openfold/np/relax/cleanup.py
openfold/np/relax/relax.py
openfold/np/relax/utils.py
openfold/resources/__init__.py
openfold/utils/feats.py
openfold/utils/loss.py
openfold/utils/rigid_utils.py
openfold/utils/tensor_utils.py
pd_ligand_mpnn-0.1.2.dist-info/METADATA
pd_ligand_mpnn-0.1.2.dist-info/WHEEL
pd_ligand_mpnn-0.1.2.dist-info/entry_points.txt
pd_ligand_mpnn-0.1.2.dist-info/licenses/LICENSE
pd_ligand_mpnn-0.1.2.dist-info/RECORD
