Metadata-Version: 2.4
Name: pd-ligand-mpnn
Version: 0.1.2
License-File: LICENSE
Requires-Python: <3.10,>=3.9
Requires-Dist: biopython
Requires-Dist: dm-tree==0.1.8
Requires-Dist: filelock
Requires-Dist: fsspec
Requires-Dist: jinja2
Requires-Dist: markupsafe
Requires-Dist: ml-collections==0.1.1
Requires-Dist: mpmath==1.3.0
Requires-Dist: networkx==3.2.1
Requires-Dist: numpy==1.23.5
Requires-Dist: nvidia-cublas-cu12==12.1.3.1
Requires-Dist: nvidia-cuda-cupti-cu12==12.1.105
Requires-Dist: nvidia-cuda-nvrtc-cu12==12.1.105
Requires-Dist: nvidia-cuda-runtime-cu12==12.1.105
Requires-Dist: nvidia-cudnn-cu12==8.9.2.26
Requires-Dist: nvidia-cufft-cu12==11.0.2.54
Requires-Dist: nvidia-curand-cu12==10.3.2.106
Requires-Dist: nvidia-cusolver-cu12==11.4.5.107
Requires-Dist: nvidia-cusparse-cu12==12.1.0.106
Requires-Dist: nvidia-nccl-cu12==2.19.3
Requires-Dist: nvidia-nvjitlink-cu12==12.4.99
Requires-Dist: nvidia-nvtx-cu12==12.1.105
Requires-Dist: prody==2.4.1
Requires-Dist: pyparsing==3.1.1
Requires-Dist: scipy==1.12.0
Requires-Dist: sympy==1.12
Requires-Dist: torch==2.2.1
Requires-Dist: triton==2.2.0
Requires-Dist: typing-extensions
